pip_package_template_docker/__init__.py
pip_package_template_docker-2023.4.23.post1.dist-info/LICENSE
pip_package_template_docker-2023.4.23.post1.dist-info/METADATA
pip_package_template_docker-2023.4.23.post1.dist-info/WHEEL
pip_package_template_docker-2023.4.23.post1.dist-info/top_level.txt
pip_package_template_docker-2023.4.23.post1.dist-info/RECORD
